novadb/__init__.py
novadb/configurator.py
novadb/connection.py
novadb/executor.py
novadb/ocl.ini
novadb/parser.py
novadb/query.py
novadb-1.1.2.dist-info/LICENSE
novadb-1.1.2.dist-info/METADATA
novadb-1.1.2.dist-info/WHEEL
novadb-1.1.2.dist-info/top_level.txt
novadb-1.1.2.dist-info/RECORD
